STI_DAC.v
module STI_DAC(clk ,reset, load, pi_data, pi_length, pi_fill, pi_msb, pi_low, pi_end,
	       so_data, so_valid,
	       oem_finish, oem_dataout, oem_addr,
	       odd1_wr, odd2_wr, odd3_wr, odd4_wr, even1_wr, even2_wr, even3_wr, even4_wr);

input		clk, reset;
input		load, pi_msb, pi_low, pi_end; 
input	[15:0]	pi_data;
input	[1:0]	pi_length;
input		pi_fill;
output		so_data, so_valid;

output  oem_finish, odd1_wr, odd2_wr, odd3_wr, odd4_wr, even1_wr, even2_wr, even3_wr, even4_wr;
output [4:0] oem_addr;
output [7:0] oem_dataout;

//==============================================================================
reg so_data, so_valid;
reg oem_finish, odd1_wr, odd2_wr, odd3_wr, odd4_wr, even1_wr, even2_wr, even3_wr, even4_wr;
reg [4:0] oem_addr;
reg [7:0] oem_dataout;

reg [2:0] current_state,next_state;
parameter IDLE = 3'd0;
parameter LOAD = 3'd1;
parameter SERIAL_OUT = 3'd2;
parameter FINISH = 3'd3;

reg [31:0] data_buffer;
reg [4:0] serial_counter,pi_length_bit;
//state switch
always@(posedge clk or posedge reset)
begin
	if(reset) current_state <= IDLE;
	else current_state <= next_state;
end

//next state logic
always@(*)
begin
	case(current_state)
	IDLE:
	begin
		if(load) next_state = LOAD;
		else next_state = IDLE;
	end
	LOAD:
	begin
		next_state = SERIAL_OUT;
	end
	SERIAL_OUT:
	begin
		if(serial_counter == 4'd0) next_state = IDLE;
		else next_state = SERIAL_OUT;
	end
	FINISH:
	begin
		next_state = FINISH;
	end
	default: next_state = IDLE;
	endcase
end

//pi_length_bit
always@(*)
begin
	case(pi_length)
	2'b00: pi_length_bit = 5'd7;
	2'b01: pi_length_bit = 5'd15; 
	2'b10: pi_length_bit = 5'd23;
	2'b11: pi_length_bit = 5'd31;
	default: pi_length_bit = 5'd0;
	endcase
end

//data_buffer 31 is MSB , 0 is LSB
always@(*)
begin
	case(pi_length)
	2'b00: //8bit
	begin
		if(pi_low) 
		begin
			data_buffer[31:24] = pi_data[15:8];
			data_buffer[23:0] = 24'd0; //prevent latch
		end
		else
		begin
			data_buffer[31:24] = pi_data[7:0];
			data_buffer[23:0] = 24'd0; //prevent latch
		end
	end
	2'b01: //16bit
	begin
		data_buffer[31:16] = pi_data[15:0];
		data_buffer[15:0] = 16'd0; //prevent latch
	end
	2'b10: //24bit
	begin
		if(pi_fill)
		begin
			data_buffer[31:16] = pi_data[15:0];
			data_buffer[15:0] = 16'd0;
		end
		else 
		begin
			data_buffer[31:24] = 8'd0;
			data_buffer[23:8] = pi_data[15:0];
			data_buffer[7:0] = 8'd0; //prevent latch
		end
	end
	2'b11: //32bit
	begin
		if(pi_fill)
		begin
			data_buffer[31:16] = pi_data[15:0];
			data_buffer[15:0] = 16'd0;
		end
		else
		begin
			data_buffer[31:16] = 16'd0;
			data_buffer[15:0] = pi_data[15:0];
		end
	end
	default: data_buffer = 32'd0;
	endcase
end

//serial_counter
always@(posedge clk or posedge reset)
begin
	if(reset) serial_counter <= 5'd31;
	else if(next_state == LOAD)
	begin
		case(pi_length)
		2'b00: serial_counter <= 5'd7;
		2'b01: serial_counter <= 5'd15; 
		2'b10: serial_counter <= 5'd23;
		2'b11: serial_counter <= 5'd31;
		endcase
	end
	else if(current_state == SERIAL_OUT) serial_counter <= serial_counter - 4'd1;
end

//so_valid
always@(posedge clk or posedge reset)
begin
	if(reset) so_valid <= 1'd0;
	else if(next_state == SERIAL_OUT) so_valid <= 1'd1;
	else so_valid <= 1'd0;
end

//data_buffer_index
reg [4:0] data_buffer_index;
always@(posedge clk or posedge reset)
begin
	if(reset) data_buffer_index = 5'd0;
	else if(next_state == LOAD)
	begin
		if(pi_msb) data_buffer_index <= 5'd31;
		else
		begin
			case(pi_length)
			2'b00: data_buffer_index <= 5'd24;
			2'b01: data_buffer_index <= 5'd16; 
			2'b10: data_buffer_index <= 5'd8;
			2'b11: data_buffer_index <= 5'd0;
			endcase
		end
	end
	else if(next_state == SERIAL_OUT)
	begin
		if(pi_msb) data_buffer_index <= data_buffer_index - 5'd1;
		else data_buffer_index <= data_buffer_index + 5'd1;
	end
	
	
end

//so_data
always@(posedge clk or posedge reset)
begin
	if(reset) so_data <= 1'd0;
	else so_data <= data_buffer[data_buffer_index];
end



endmodule

testfixture2.v
`timescale 1ns/10ps
`define SDFFILE    "./syn/STI_DAC_syn.sdf"    // Modify your sdf file name
`define cycle 10
`define terminate_cycle 100000

module testfixture2;



	`define Pattern "./dat/Pattern2.dat"
	`define Stimulus "./dat/Stimulus2.dat"
	`define Expected "./dat/Expected2_so.dat"
	`define Pat_num 34
	`define Exp_num 767
	`define Pixel "./dat/Expected2_pixel.dat"
	`define odd1 "./dat/Expected2_odd_1.dat"
	`define odd2 "./dat/Expected2_odd_2.dat"
	`define odd3 "./dat/Expected2_odd_3.dat"
	`define odd4 "./dat/Expected2_odd_4.dat" 
	`define even1 "./dat/Expected2_even_1.dat"
	`define even2 "./dat/Expected2_even_2.dat"
	`define even3 "./dat/Expected2_even_3.dat"
	`define even4 "./dat/Expected2_even_4.dat"



reg [15:0] stimulus_in, pattern_in;

reg Exp_so;

reg pi_end;

reg load, reset;
reg clk = 0;
wire [1:0] pi_length = stimulus_in[13:12];
wire fill_mode = stimulus_in[8];
wire msb_first = stimulus_in[4];
wire low_en = stimulus_in[0];
wire [15:0] pi_data = pattern_in;
wire 		so_data, so_valid;

wire  pixel_finish, pixel_wr, oem_finish, odd1_wr, odd2_wr , odd3_wr , odd4_wr , even1_wr , even2_wr , even3_wr, even4_wr;
wire [7:0] pixel_addr;
wire [7:0] pixel_dataout;
wire [4:0] oem_addr;
wire [7:0] oem_dataout;

integer pp, pixel_err;
reg [7:0] PIXEL_MEM [0 : 233];
integer oo1, oo1_err, oo2, oo2_err, oo3, oo3_err, oo4, oo4_err;
reg [7:0] ODD1_MEM [0 : 31];
reg [7:0] ODD2_MEM [0 : 31];
reg [7:0] ODD3_MEM [0 : 31];
reg [7:0] ODD4_MEM [0 : 31];
integer ee1, ee1_err, ee2, ee2_err, ee3, ee3_err, ee4, ee4_err;
reg [7:0] EVEN1_MEM [0 : 31];
reg [7:0] EVEN2_MEM [0 : 31];
reg [7:0] EVEN3_MEM [0 : 31];
reg [7:0] EVEN4_MEM [0 : 31];
always@(posedge pixel_wr) PIXEL_MEM[pixel_addr] = pixel_dataout;
always@(posedge odd1_wr) ODD1_MEM[oem_addr] = oem_dataout;
always@(posedge odd2_wr) ODD2_MEM[oem_addr] = oem_dataout;
always@(posedge odd3_wr) ODD3_MEM[oem_addr] = oem_dataout;
always@(posedge odd4_wr) ODD4_MEM[oem_addr] = oem_dataout;
always@(posedge even1_wr) EVEN1_MEM[oem_addr] = oem_dataout;
always@(posedge even2_wr) EVEN2_MEM[oem_addr] = oem_dataout;
always@(posedge even3_wr) EVEN3_MEM[oem_addr] = oem_dataout;
always@(posedge even4_wr) EVEN4_MEM[oem_addr] = oem_dataout;

// ---------------------------------------- DUT instance ----------------------------------------------------------------------------------------------------
STI_DAC u_rtl(.clk(clk) ,.reset(reset), .load(load), .pi_data(pi_data), .pi_length(pi_length), 
	      .pi_fill(fill_mode), .pi_msb(msb_first), .pi_low(low_en), .pi_end(pi_end),
	      .so_data(so_data), .so_valid(so_valid),  
	      .oem_finish(oem_finish), .oem_addr(oem_addr), .oem_dataout(oem_dataout), 
	      .odd1_wr(odd1_wr), .odd2_wr(odd2_wr), .odd3_wr(odd3_wr), .odd4_wr(odd4_wr), 
	      .even1_wr(even1_wr), .even2_wr(even2_wr), .even3_wr(even3_wr), .even4_wr(even4_wr));

`ifdef SDF
initial $sdf_annotate(`SDFFILE, u_rtl);
`endif



reg [15:0] 	Pat_memory [0:`Pat_num];
reg 	   	Exp_memory [0:`Exp_num];
reg		Real_memory [0:`Exp_num];
reg [15:0] 	Sti_memory [0:`Pat_num];
reg [7:0] 	Exp_pixel [0:233];
reg [7:0] Exp_odd01 [0:31];
reg [7:0] Exp_odd02 [0:31];
reg [7:0] Exp_odd03 [0:31];
reg [7:0] Exp_odd04 [0:31];
reg [7:0] Exp_even01 [0:31];
reg [7:0] Exp_even02 [0:31];
reg [7:0] Exp_even03 [0:31];
reg [7:0] Exp_even04 [0:31];
initial begin
	$readmemh(`Pattern, Pat_memory);
	$readmemh(`Stimulus, Sti_memory);
	$readmemh(`Expected, Exp_memory);
	$readmemh(`Pixel, Exp_pixel);
	$readmemh(`odd1, Exp_odd01); 
	$readmemh(`odd2, Exp_odd02); 
	$readmemh(`odd3, Exp_odd03); 
	$readmemh(`odd4, Exp_odd04);
	$readmemh(`even1, Exp_even01); 
	$readmemh(`even2, Exp_even02); 
	$readmemh(`even3, Exp_even03); 
	$readmemh(`even4, Exp_even04);
	$display("--------------------------- Simulation Pattern is ready !!---------------------------");
end



always #(`cycle/2) clk = ~clk;

integer k;
integer i;
integer err_cnt;
integer c;
reg so_pass, Real_so, so_exp;
//------------- SPI module test ------------------------------------------------------------------------------------------------------------------------
initial begin
	//$fsdbDumpfile("STI_DAC.fsdb");
	//$fsdbDumpvars;
	$dumpfile("STI_DAC.vcd");
	$dumpvars;
      $display("--------------------------- [ testfixture2.v ] Simulation START !!---------------------------");
      $timeformat(-9, 1, " ns", 9); //Display time in nanoseconds
      
      err_cnt = 0;   
      reset = 0;
      load = 0;
      # `cycle;
      stimulus_in = 0;
      pattern_in = 0;
      reset = 1; 
      pi_end = 0;
      # `cycle;
      reset = 0; 
      i = 0;
      
        $display("--------------------------- Simulation at parallel data input stage  !!---------------------------");
	for (k = 0; k <= `Pat_num; k = k+1)
	begin      
		
			@(negedge clk)
			//change inputs at strobe point
          		#(`cycle/4) load = 1;
				stimulus_in = Sti_memory[k];                
      				pattern_in = Pat_memory[k];
			#(`cycle) load = 0;
          		//Wait for PSI to process inputs
			if (k==`Pat_num) pi_end = 1;
          		wait(so_valid) 
			record_outputs; //call a task to verify outputs
	
	end
	
	// check_outputs	
	$display("--------------------------- Simulation at serial data output and result verify !! ---------------------------");
	for (c = 0; c <= `Exp_num; c = c+1) 
	begin
		
		if (Real_memory[c] == Exp_memory[c]) begin  so_pass = Real_memory[c]; so_exp =  Exp_memory[c]; end
		else begin err_cnt = err_cnt + 1;  
			$display("---------- ERROR at pattern No. %d,  REAL OUTPUT : so_data = %b,  EXPECTED OUTPUT so_data = %b\n",
      			c, Real_memory[c], Exp_memory[c]); end
	end 
	
     #`cycle 
     $display("--------------------------- so_data simulation FINISH !!---------------------------");
     if (err_cnt) begin 
     	$display("============================================================================");
     	$display("\n (T_T)  The simulation result of so_data is FAIL!!! there were %d errors in all.\n", err_cnt);
	$display("============================================================================");
	end
     else begin 
     	$display("============================================================================");
	$display("\n \\(^o^)/  The simulation result of so_data is PASS!!!\n");
	$display("============================================================================");
	end
     wait ( oem_finish );
     #(`cycle*0.25) ;
     $display("--------------------------- OM-memory and EM-memory simulation FINISH !!---------------------------");
     if ( oo1_err || oo2_err || oo3_err || oo4_err || ee1_err || ee2_err || ee3_err || ee4_err) begin 
     	$display("============================================================================");
     	$display("\n (T_T)  The simulation result of OM-memory and EM-memory is FAIL!!! Please debug your RTL code !!.\n");
	$display("============================================================================");
	end
     else begin 
     	$display("============================================================================");
	$display("\n \\(^o^)/  The simulation result of OM-memory and EM-memory is PASS!!!\n");
	$display("============================================================================");
	end
     //#`cycle    
     $finish;
end


initial begin 
	#`terminate_cycle;
	$display("================================================================================================================");
	$display("--------------------------- (/`n`)/ ~#  There was something wrong with your code !! ---------------------------"); 
	$display("--------------------------- The simulation can't finished!!, Please check it !!! ---------------------------"); 
	$display("================================================================================================================");
	$finish;
end

//--------------------------- check SPI outputs -----------------------------------------------------------------
  task record_outputs;	
  	while(so_valid)  begin
  		@(negedge clk); 
		if (so_valid) begin
		Real_memory[i] = so_data;
		Real_so = Real_memory[i];
		i = i+1;
  		end
	end 
  endtask




//=========================================================================================================================================
//=========================================================================================================================================
//=========================================================================================================================================
//----------------------- Check Pixel data -----------------------------------------------------------------------------------------------------

/*
initial begin
	pixel_err  = 0;
	wait(pixel_finish)
	for (pp=0; pp<=233; pp=pp+1) begin
		if (Exp_pixel[pp] == PIXEL_MEM[pp]);
		else begin
			pixel_err = pixel_err + 1;
			$display("---------- ERROR AT %t,  ERROR DATA : the real data at pixel address %d = %h,  EXPECTED DATA  = %h\n",
			$realtime, pp, PIXEL_MEM[pp], Exp_pixel[pp]);
		end
	end
end
*/
//----------------------- Check EVEN memory -----------------------------------------------------------------------------------------------------
initial begin
	ee4_err = 0;
	wait(reset); wait(!reset); wait(load); wait(!load);
	wait(oem_finish);
	for (ee4=0; ee4<=31; ee4=ee4+1) begin
		if (Exp_even04[ee4] == EVEN4_MEM[ee4]);
		else begin
			ee4_err = ee4_err + 1;
			$display("---------- ERROR AT %t,  ERROR DATA : the real data at EVEN4_MEM address %d = %h, but the EXPECTED DATA  = %h\n",
			$realtime, ee4, EVEN4_MEM[ee4], Exp_even04[ee4]);
		end
	end
end
initial begin
	ee3_err = 0;
	wait(reset); wait(!reset); wait(load); wait(!load);
	wait(oem_finish);
	for (ee3=0; ee3<=31; ee3=ee3+1) begin
		if (Exp_even03[ee3] == EVEN3_MEM[ee3]);
		else begin
			ee3_err = ee3_err + 1;
			$display("---------- ERROR AT %t,  ERROR DATA : the real data at EVEN3_MEM address %d = %h, but the EXPECTED DATA  = %h\n",
			$realtime, ee3, EVEN3_MEM[ee3], Exp_even03[ee3]);
		end
	end
end
initial begin
	ee2_err = 0;
	wait(reset); wait(!reset); wait(load); wait(!load);
	wait(oem_finish);
	for (ee2=0; ee2<=31; ee2=ee2+1) begin
		if (Exp_even02[ee2] == EVEN2_MEM[ee2]);
		else begin
			ee2_err = ee2_err + 1;
			$display("---------- ERROR AT %t,  ERROR DATA : the real data at EVEN2_MEM address %d = %h, but the EXPECTED DATA  = %h\n",
			$realtime, ee2, EVEN2_MEM[ee2], Exp_even02[ee2]);
		end
	end
end
initial begin
	ee1_err = 0;
	wait(reset); wait(!reset); wait(load); wait(!load);
	wait(oem_finish);
	for (ee1=0; ee1<=31; ee1=ee1+1) begin
		if (Exp_even01[ee1] == EVEN1_MEM[ee1]);
		else begin
			ee1_err = ee1_err + 1;
			$display("---------- ERROR AT %t,  ERROR DATA : the real data at EVEN1_MEM address %d = %h, but the EXPECTED DATA  = %h\n",
			$realtime, ee1, EVEN1_MEM[ee1], Exp_even01[ee1]);
		end
	end
end

//----------------------- Check ODD memory -----------------------------------------------------------------------------------------------------
initial begin
	oo4_err = 0;
	wait(reset); wait(!reset); wait(load); wait(!load);
	wait(oem_finish);
	for (oo4=0; oo4<=31; oo4=oo4+1) begin
		if (Exp_odd04[oo4] == ODD4_MEM[oo4]);
		else begin
			oo4_err = oo4_err + 1;
			$display("---------- ERROR AT %t,  ERROR DATA : the real data at ODD4_MEM address %d = %h, but the EXPECTED DATA  = %h\n",
			$realtime, oo4, ODD4_MEM[oo4], Exp_odd04[oo4]);
		end
	end
end
initial begin
	oo3_err = 0;
	wait(reset); wait(!reset); wait(load); wait(!load);
	wait(oem_finish);
	for (oo3=0; oo3<=31; oo3=oo3+1) begin 
		if (Exp_odd03[oo3] == ODD3_MEM[oo3]);
		else begin
			oo3_err = oo3_err + 1;
			$display("---------- ERROR AT %t,  ERROR DATA : the real data at ODD3_MEM address %d = %h, but the EXPECTED DATA  = %h\n",
			$realtime, oo3, ODD3_MEM[oo3], Exp_odd03[oo3]);
		end
	end
end
initial begin
	oo2_err = 0;
	wait(reset); wait(!reset); wait(load); wait(!load);
	wait(oem_finish);
	for (oo2=0; oo2<=31; oo2=oo2+1) begin
		if (Exp_odd02[oo2] == ODD2_MEM[oo2]);
		else begin
			oo2_err = oo2_err + 1;
			$display("---------- ERROR AT %t,  ERROR DATA : the real data at ODD2_MEM address %d = %h, but the EXPECTED DATA  = %h\n",
			$realtime, oo2, ODD2_MEM[oo2], Exp_odd02[oo2]);
		end
	end
end
initial begin
	oo1_err = 0;
	wait(reset); wait(!reset); wait(load); wait(!load);
	wait(oem_finish);
	for (oo1=0; oo1<=31; oo1=oo1+1) begin
		if (Exp_odd01[oo1] == ODD1_MEM[oo1]);
		else begin
			oo1_err = oo1_err + 1;
			$display("---------- ERROR AT %t,  ERROR DATA : the real data at ODD1_MEM address %d = %h, but the EXPECTED DATA  = %h\n",
			$realtime, oo1, ODD1_MEM[oo1], Exp_odd01[oo1]);
		end
	end
end








endmodule

STI_DAC.vcd
$date
	Mon Aug 31 01:00:56 2020
$end
$version
	Icarus Verilog
$end
$timescale
	10ps
$end
$scope module testfixture2 $end
$var wire 16 ! pi_data [15:0] $end
$var wire 8 " pixel_addr [7:0] $end
$var wire 8 # pixel_dataout [7:0] $end
$var wire 1 $ pixel_wr $end
$var wire 1 % so_valid $end
$var wire 1 & so_data $end
$var wire 2 ' pi_length [1:0] $end
$var wire 1 ( oem_finish $end
$var wire 8 ) oem_dataout [7:0] $end
$var wire 5 * oem_addr [4:0] $end
$var wire 1 + odd4_wr $end
$var wire 1 , odd3_wr $end
$var wire 1 - odd2_wr $end
$var wire 1 . odd1_wr $end
$var wire 1 / msb_first $end
$var wire 1 0 low_en $end
$var wire 1 1 fill_mode $end
$var wire 1 2 even4_wr $end
$var wire 1 3 even3_wr $end
$var wire 1 4 even2_wr $end
$var wire 1 5 even1_wr $end
$var reg 1 6 Real_so $end
$var reg 1 7 clk $end
$var reg 1 8 load $end
$var reg 16 9 pattern_in [15:0] $end
$var reg 1 : pi_end $end
$var reg 1 ; reset $end
$var reg 1 < so_exp $end
$var reg 1 = so_pass $end
$var reg 16 > stimulus_in [15:0] $end
$var integer 32 ? c [31:0] $end
$var integer 32 @ ee1 [31:0] $end
$var integer 32 A ee1_err [31:0] $end
$var integer 32 B ee2 [31:0] $end
$var integer 32 C ee2_err [31:0] $end
$var integer 32 D ee3 [31:0] $end
$var integer 32 E ee3_err [31:0] $end
$var integer 32 F ee4 [31:0] $end
$var integer 32 G ee4_err [31:0] $end
$var integer 32 H err_cnt [31:0] $end
$var integer 32 I i [31:0] $end
$var integer 32 J k [31:0] $end
$var integer 32 K oo1 [31:0] $end
$var integer 32 L oo1_err [31:0] $end
$var integer 32 M oo2 [31:0] $end
$var integer 32 N oo2_err [31:0] $end
$var integer 32 O oo3 [31:0] $end
$var integer 32 P oo3_err [31:0] $end
$var integer 32 Q oo4 [31:0] $end
$var integer 32 R oo4_err [31:0] $end
$scope module u_rtl $end
$var wire 1 7 clk $end
$var wire 1 8 load $end
$var wire 16 S pi_data [15:0] $end
$var wire 1 : pi_end $end
$var wire 1 1 pi_fill $end
$var wire 2 T pi_length [1:0] $end
$var wire 1 0 pi_low $end
$var wire 1 / pi_msb $end
$var wire 1 ; reset $end
$var reg 3 U current_state [2:0] $end
$var reg 32 V data_buffer [31:0] $end
$var reg 5 W data_buffer_index [4:0] $end
$var reg 1 5 even1_wr $end
$var reg 1 4 even2_wr $end
$var reg 1 3 even3_wr $end
$var reg 1 2 even4_wr $end
$var reg 3 X next_state [2:0] $end
$var reg 1 . odd1_wr $end
$var reg 1 - odd2_wr $end
$var reg 1 , odd3_wr $end
$var reg 1 + odd4_wr $end
$var reg 5 Y oem_addr [4:0] $end
$var reg 8 Z oem_dataout [7:0] $end
$var reg 1 ( oem_finish $end
$var reg 5 [ pi_length_bit [4:0] $end
$var reg 5 \ serial_counter [4:0] $end
$var reg 1 & so_data $end
$var reg 1 % so_valid $end
$upscope $end
$scope task record_outputs $end
$upscope $end
$upscope $end
$enddefinitions $end
#0
$dumpvars
bx \
bx [
bx Z
bx Y
b0 X
bx W
bx V
bx U
bx T
bx S
b0 R
bx Q
b0 P
bx O
b0 N
bx M
b0 L
bx K
bx J
bx I
b0 H
b0 G
bx F
b0 E
bx D
b0 C
bx B
b0 A
bx @
bx ?
bx >
x=
x<
0;
x:
bx 9
08
07
x6
x5
x4
x3
x2
x1
x0
x/
x.
x-
x,
x+
bx *
bx )
x(
bx '
x&
x%
z$
bz #
bz "
bx !
$end
#500
b0 U
0%
17
#1000
0&
b11111 \
b111 [
b0 W
b0 V
b0 '
b0 T
01
0/
00
07
0:
1;
b0 !
b0 S
b0 9
b0 >
#1500
17
#2000
07
b0 J
b0 I
0;
#2200
b11111 [
b10001001000100000000000000000 V
b11 '
b11 T
11
1/
b1 X
b1000100100010 !
b1000100100010 S
b1000100100010 9
b11000100010000 >
18
#2500
b10 X
b11111 W
b1 U
17
#3000
07
#3200
08
#3500
b10 U
1%
b11110 W
17
#4000
b1 I
06
07
#4500
b11101 W
b11110 \
17
#5000
b10 I
07
#5500
b11101 \
b11100 W
17
#6000
b11 I
07
#6500
1&
b11011 W
b11100 \
17
#7000
b100 I
16
07
#7500
b11011 \
b11010 W
0&
17
#8000
b101 I
06
07
#8500
b11001 W
b11010 \
17
#9000
b110 I
07
#9500
b11001 \
b11000 W
17
#10000
b111 I
07
#10500
1&
b10111 W
b11000 \
17
#11000
b1000 I
16
07
#11500
b10111 \
b10110 W
0&
17
#12000
b1001 I
06
07
#12500
b10101 W
b10110 \
17
#13000
b1010 I
07
#13500
b10101 \
b10100 W
1&
17
#14000
b1011 I
16
07
#14500
0&
b10011 W
b10100 \
17
#15000
b1100 I
06
07
#15500
b10011 \
b10010 W
17
#16000
b1101 I
07
#16500
b10001 W
b10010 \
17
#17000
b1110 I
07
#17500
b10001 \
b10000 W
1&
17
#18000
b1111 I
16
07
#18500
0&
b1111 W
b10000 \
17
#19000
b10000 I
06
07
#19500
b1111 \
b1110 W
17
#20000
b10001 I
07
#20500
b1101 W
b1110 \
17
#21000
b10010 I
07
#21500
b1101 \
b1100 W
17
#22000
b10011 I
07
#22500
b1011 W
b1100 \
17
#23000
b10100 I
07
#23500
b1011 \
b1010 W
17
#24000
b10101 I
07
#24500
b1001 W
b1010 \
17
#25000
b10110 I
07
#25500
b1001 \
b1000 W
17
#26000
b10111 I
07
#26500
b111 W
b1000 \
17
#27000
b11000 I
07
#27500
b111 \
b110 W
17
#28000
b11001 I
07
#28500
b101 W
b110 \
17
#29000
b11010 I
07
#29500
b101 \
b100 W
17
#30000
b11011 I
07
#30500
b11 W
b100 \
17
#31000
b11100 I
07
#31500
b11 \
b10 W
17
#32000
b11101 I
07
#32500
b1 W
b10 \
17
#33000
b11110 I
07
#33500
b1 \
b0 W
17
#34000
b11111 I
07
#34500
b0 X
b11111 W
b0 \
17
#35000
b100000 I
07
#35500
b0 U
b11111 \
0%
17
#36000
b1 J
07
#36500
17
#37000
07
#37200
b110011010001000000000000000000 V
0/
b1 X
b11001101000100 !
b11001101000100 S
b11001101000100 9
b11000100000000 >
18
#37500
b10 X
b1 U
b0 W
17
#38000
07
#38200
08
#38500
b1 W
1%
b10 U
17
#39000
b100001 I
07
#39500
b11110 \
b10 W
17
#40000
b100010 I
07
#40500
b11 W
b11101 \
17
#41000
b100011 I
07
#41500
b11100 \
b100 W
17
#42000
b100100 I
07
#42500
b101 W
b11011 \
17
#43000
b100101 I
07
#43500
b11010 \
b110 W
17
#44000
b100110 I
07
#44500
b111 W
b11001 \
17
#45000
b100111 I
07
#45500
b11000 \
b1000 W
17
#46000
b101000 I
07
#46500
b1001 W
b10111 \
17
#47000
b101001 I
07
#47500
b10110 \
b1010 W
17
#48000
b101010 I
07
#48500
b1011 W
b10101 \
17
#49000
b101011 I
07
#49500
b10100 \
b1100 W
17
#50000
b101100 I
07
#50500
b1101 W
b10011 \
17
#51000
b101101 I
07
#51500
b10010 \
b1110 W
17
#52000
b101110 I
07
#52500
b1111 W
b10001 \
17
#53000
b101111 I
07
#53500
b10000 \
b10000 W
17
#54000
b110000 I
07
#54500
b10001 W
b1111 \
17
#55000
b110001 I
07
#55500
b1110 \
b10010 W
17
#56000
b110010 I
07
#56500
1&
b10011 W
b1101 \
17
#57000
b110011 I
16
07
#57500
b1100 \
b10100 W
0&
17
#58000
b110100 I
06
07
#58500
b10101 W
b1011 \
17
#59000
b110101 I
07
#59500
b1010 \
b10110 W
17
#60000
b110110 I
07
#60500
1&
b10111 W
b1001 \
17
#61000
b110111 I
16
07
#61500
b1000 \
b11000 W
0&
17
#62000
b111000 I
06
07
#62500
1&
b11001 W
b111 \
17
#63000
b111001 I
16
07
#63500
b110 \
b11010 W
17
#64000
b111010 I
07
#64500
0&
b11011 W
b101 \
17
#65000
b111011 I
06
07
#65500
b100 \
b11100 W
17
#66000
b111100 I
07
#66500
1&
b11101 W
b11 \
17
#67000
b111101 I
16
07
#67500
b10 \
b11110 W
17
#68000
b111110 I
07
#68500
0&
b11111 W
b1 \
17
#69000
b111111 I
06
07
#69500
b0 X
b0 \
b0 W
17
#70000
b1000000 I
07
#70500
0%
b11111 \
b0 U
17
#71000
b10 J
07
#71500
17
#72000
07
#72200
b111 [
b1100110000000000000000000000000 V
b0 '
b0 T
b1 X
b101010101100110 !
b101010101100110 S
b101010101100110 9
b100000000 >
18
#72500
b10 X
b11000 W
b111 \
b1 U
17
#73000
07
#73200
08
#73500
b10 U
1%
b11001 W
17
#74000
b1000001 I
07
#74500
1&
b11010 W
b110 \
17
#75000
b1000010 I
16
07
#75500
b101 \
b11011 W
17
#76000
b1000011 I
07
#76500
0&
b11100 W
b100 \
17
#77000
b1000100 I
06
07
#77500
b11 \
b11101 W
17
#78000
b1000101 I
07
#78500
1&
b11110 W
b10 \
17
#79000
b1000110 I
16
07
#79500
b1 \
b11111 W
17
#80000
b1000111 I
07
#80500
b0 X
0&
b0 W
b0 \
17
#81000
b1001000 I
06
07
#81500
b0 U
b11111 \
0%
17
#82000
b11 J
07
#82500
17
#83000
07
#83200
b11111 [
b111011110001000 V
b11 '
b11 T
01
b1 X
b111011110001000 !
b111011110001000 S
b111011110001000 9
b11000000000000 >
18
#83500
b10 X
b1 U
17
#84000
07
#84200
08
#84500
b1 W
1%
b10 U
17
#85000
b1001001 I
07
#85500
b11110 \
b10 W
17
#86000
b1001010 I
07
#86500
b11 W
b11101 \
17
#87000
b1001011 I
07
#87500
b11100 \
b100 W
1&
17
#88000
b1001100 I
16
07
#88500
0&
b101 W
b11011 \
17
#89000
b1001101 I
06
07
#89500
b11010 \
b110 W
17
#90000
b1001110 I
07
#90500
b111 W
b11001 \
17
#91000
b1001111 I
07
#91500
b11000 \
b1000 W
1&
17
#92000
b1010000 I
16
07
#92500
b1001 W
b10111 \
17
#93000
b1010001 I
07
#93500
b10110 \
b1010 W
17
#94000
b1010010 I
07
#94500
b1011 W
b10101 \
17
#95000
b1010011 I
07
#95500
b10100 \
b1100 W
0&
17
#96000
b1010100 I
06
07
#96500
1&
b1101 W
b10011 \
17
#97000
b1010101 I
16
07
#97500
b10010 \
b1110 W
17
#98000
b1010110 I
07
#98500
b1111 W
b10001 \
17
#99000
b1010111 I
07
#99500
b10000 \
b10000 W
0&
17
#100000
b1011000 I
06
07
#100500
b10001 W
b1111 \
17
#101000
b1011001 I
07
#101500
b1110 \
b10010 W
17
#102000
b1011010 I
07
#102500
b10011 W
b1101 \
17
#103000
b1011011 I
07
#103500
b1100 \
b10100 W
17
#104000
b1011100 I
07
#104500
b10101 W
b1011 \
17
#105000
b1011101 I
07
#105500
b1010 \
b10110 W
17
#106000
b1011110 I
07
#106500
b10111 W
b1001 \
17
#107000
b1011111 I
07
#107500
b1000 \
b11000 W
17
#108000
b1100000 I
07
#108500
b11001 W
b111 \
17
#109000
b1100001 I
07
#109500
b110 \
b11010 W
17
#110000
b1100010 I
07
#110500
b11011 W
b101 \
17
#111000
b1100011 I
07
#111500
b100 \
b11100 W
17
#112000
b1100100 I
07
#112500
b11101 W
b11 \
17
#113000
b1100101 I
07
#113500
b10 \
b11110 W
17
#114000
b1100110 I
07
#114500
b11111 W
b1 \
17
#115000
b1100111 I
07
#115500
b0 X
b0 \
b0 W
17
#116000
b1101000 I
07
#116500
0%
b11111 \
b0 U
17
#117000
b100 J
07
#117500
17
#118000
07
#118200
b10111 [
b10011001101010100000000000000000 V
b10 '
b10 T
11
1/
b1 X
b1001100110101010 !
b1001100110101010 S
b1001100110101010 9
b10000100010000 >
18
#118500
b10 X
b11111 W
b10111 \
b1 U
17
#119000
07
#119200
08
#119500
b10 U
1%
b11110 W
1&
17
#120000
b1101001 I
16
07
#120500
0&
b11101 W
b10110 \
17
#121000
b1101010 I
06
07
#121500
b10101 \
b11100 W
17
#122000
b1101011 I
07
#122500
1&
b11011 W
b10100 \
17
#123000
b1101100 I
16
07
#123500
b10011 \
b11010 W
17
#124000
b1101101 I
07
#124500
0&
b11001 W
b10010 \
17
#125000
b1101110 I
06
07
#125500
b10001 \
b11000 W
17
#126000
b1101111 I
07
#126500
1&
b10111 W
b10000 \
17
#127000
b1110000 I
16
07
#127500
b1111 \
b10110 W
17
#128000
b1110001 I
07
#128500
0&
b10101 W
b1110 \
17
#129000
b1110010 I
06
07
#129500
b1101 \
b10100 W
1&
17
#130000
b1110011 I
16
07
#130500
0&
b10011 W
b1100 \
17
#131000
b1110100 I
06
07
#131500
b1011 \
b10010 W
1&
17
#132000
b1110101 I
16
07
#132500
0&
b10001 W
b1010 \
17
#133000
b1110110 I
06
07
#133500
b1001 \
b10000 W
1&
17
#134000
b1110111 I
16
07
#134500
0&
b1111 W
b1000 \
17
#135000
b1111000 I
06
07
#135500
b111 \
b1110 W
17
#136000
b1111001 I
07
#136500
b1101 W
b110 \
17
#137000
b1111010 I
07
#137500
b101 \
b1100 W
17
#138000
b1111011 I
07
#138500
b1011 W
b100 \
17
#139000
b1111100 I
07
#139500
b11 \
b1010 W
17
#140000
b1111101 I
07
#140500
b1001 W
b10 \
17
#141000
b1111110 I
07
#141500
b1 \
b1000 W
17
#142000
b1111111 I
07
#142500
b0 X
b111 W
b0 \
17
#143000
b10000000 I
07
