STI_DAC.v
module STI_DAC(clk ,reset, load, pi_data, pi_length, pi_fill, pi_msb, pi_low, pi_end,
	       so_data, so_valid,
	       oem_finish, oem_dataout, oem_addr,
	       odd1_wr, odd2_wr, odd3_wr, odd4_wr, even1_wr, even2_wr, even3_wr, even4_wr);

input		clk, reset;
input		load, pi_msb, pi_low, pi_end; 
input	[15:0]	pi_data;
input	[1:0]	pi_length;
input		pi_fill;
output		so_data, so_valid;

output  oem_finish, odd1_wr, odd2_wr, odd3_wr, odd4_wr, even1_wr, even2_wr, even3_wr, even4_wr;
output [4:0] oem_addr;
output [7:0] oem_dataout;

//==============================================================================
reg so_data, so_valid;
reg oem_finish, odd1_wr, odd2_wr, odd3_wr, odd4_wr, even1_wr, even2_wr, even3_wr, even4_wr;
reg [4:0] oem_addr;
wire [7:0] oem_dataout;

reg [2:0] current_state,next_state;
parameter IDLE = 3'd0;
parameter LOAD = 3'd1;
parameter SERIAL_OUT = 3'd2;
parameter FINISH = 3'd3;

reg [31:0] data_buffer;
reg [4:0] serial_counter,pi_length_bit;
//state switch
always@(posedge clk or posedge reset)
begin
	if(reset) current_state <= IDLE;
	else current_state <= next_state;
end

//next state logic
always@(*)
begin
	case(current_state)
	IDLE:
	begin
		if(load) next_state = LOAD;
		else next_state = IDLE;
	end
	LOAD:
	begin
		next_state = SERIAL_OUT;
	end
	SERIAL_OUT:
	begin
		if(serial_counter == 4'd0) next_state = IDLE;
		else next_state = SERIAL_OUT;
	end
	FINISH:
	begin
		next_state = FINISH;
	end
	default: next_state = IDLE;
	endcase
end

//pi_length_bit
always@(*)
begin
	case(pi_length)
	2'b00: pi_length_bit = 5'd7;
	2'b01: pi_length_bit = 5'd15; 
	2'b10: pi_length_bit = 5'd23;
	2'b11: pi_length_bit = 5'd31;
	default: pi_length_bit = 5'd0;
	endcase
end

//data_buffer 31 is MSB , 0 is LSB
always@(*)
begin
	case(pi_length)
	2'b00: //8bit
	begin
		if(pi_low) 
		begin
			data_buffer[31:24] = pi_data[15:8];
			data_buffer[23:0] = 24'd0; //prevent latch
		end
		else
		begin
			data_buffer[31:24] = pi_data[7:0];
			data_buffer[23:0] = 24'd0; //prevent latch
		end
	end
	2'b01: //16bit
	begin
		data_buffer[31:16] = pi_data[15:0];
		data_buffer[15:0] = 16'd0; //prevent latch
	end
	2'b10: //24bit
	begin
		if(pi_fill)
		begin
			data_buffer[31:16] = pi_data[15:0];
			data_buffer[15:0] = 16'd0;
		end
		else 
		begin
			data_buffer[31:24] = 8'd0;
			data_buffer[23:8] = pi_data[15:0];
			data_buffer[7:0] = 8'd0; //prevent latch
		end
	end
	2'b11: //32bit
	begin
		if(pi_fill)
		begin
			data_buffer[31:16] = pi_data[15:0];
			data_buffer[15:0] = 16'd0;
		end
		else
		begin
			data_buffer[31:16] = 16'd0;
			data_buffer[15:0] = pi_data[15:0];
		end
	end
	default: data_buffer = 32'd0;
	endcase
end

//serial_counter
always@(posedge clk or posedge reset)
begin
	if(reset) serial_counter <= 5'd31;
	else if(next_state == LOAD)
	begin
		case(pi_length)
		2'b00: serial_counter <= 5'd7;
		2'b01: serial_counter <= 5'd15; 
		2'b10: serial_counter <= 5'd23;
		2'b11: serial_counter <= 5'd31;
		endcase
	end
	else if(current_state == SERIAL_OUT) serial_counter <= serial_counter - 4'd1;
end

//so_valid
always@(posedge clk or posedge reset)
begin
	if(reset) so_valid <= 1'd0;
	else if(next_state == SERIAL_OUT) so_valid <= 1'd1;
	else so_valid <= 1'd0;
end

//data_buffer_index
reg [4:0] data_buffer_index;
always@(posedge clk or posedge reset)
begin
	if(reset) data_buffer_index = 5'd0;
	else if(next_state == LOAD)
	begin
		if(pi_msb) data_buffer_index <= 5'd31;
		else
		begin
			case(pi_length)
			2'b00: data_buffer_index <= 5'd24;
			2'b01: data_buffer_index <= 5'd16; 
			2'b10: data_buffer_index <= 5'd8;
			2'b11: data_buffer_index <= 5'd0;
			endcase
		end
	end
	else if(next_state == SERIAL_OUT)
	begin
		if(pi_msb) data_buffer_index <= data_buffer_index - 5'd1;
		else data_buffer_index <= data_buffer_index + 5'd1;
	end
	
	
end

//so_data
always@(posedge clk or posedge reset)
begin
	if(reset) so_data <= 1'd0;
	else so_data <= data_buffer[data_buffer_index];
end

//////////DAC////////
reg [7:0] DAC_buffer;  
reg [3:0] counter_16bit;
reg [3:0] counter_16bit_delay_1clk;
reg [7:0] mem_counter;
reg odd_even;

//odd_even
always@(posedge clk or posedge reset)
begin
	if(reset) odd_even <= 1'd0;
	else if(mem_counter[3:0] == 4'd7) odd_even <= 1'd1;
	else if(mem_counter[3:0] == 4'd15) odd_even <= 1'd0;

end


always@(posedge clk or posedge reset)
begin
	if(reset) DAC_buffer <= 8'd0;
	else if(so_valid)
	begin
		DAC_buffer <= DAC_buffer << 8'd1;
		DAC_buffer[0] <= so_data; 
	end
end

//cout 16bit
always@(posedge clk or posedge reset)
begin
	if(reset) counter_16bit <= 4'd0;
	else if(so_valid) counter_16bit <= counter_16bit + 4'd1;
end

//mem_counter
always@(posedge clk or posedge reset)
begin
	if(reset) mem_counter <= 8'd0;
	else if(counter_16bit == 4'd7 || counter_16bit == 4'd15) mem_counter <= mem_counter + 8'd1;
end

reg [4:0] delay_buffer;


//oem_addr
always@(posedge clk or posedge reset)
begin
	if(reset) delay_buffer <= 5'd0;
	else if(counter_16bit == 4'd15) delay_buffer <= delay_buffer + 5'd1;
end

always@(posedge clk or posedge reset)
begin
	if(reset) oem_addr <= 5'd0;
	else oem_addr <= delay_buffer;
end

//oem_dataout
/*
always@(posedge clk or posedge reset)
begin
	if(reset) oem_dataout <= 8'd0;
	else if(counter_16bit == 4'd7 || counter_16bit == 4'd15) oem_dataout <= DAC_buffer;
end*/
assign oem_dataout = DAC_buffer;

//ome_finish
always@(posedge clk or posedge reset)
begin
	if(reset) oem_finish <= 1'd0;
	else if(pi_end) oem_finish <= 1'd1;
end

//wr
always@(posedge clk or posedge reset)
begin
	if(reset) odd1_wr <= 1'd0;
	else if(mem_counter <= 8'd63 && counter_16bit == 4'd7 && odd_even == 1'd0) odd1_wr <= 1'd1;
	else if(mem_counter <= 8'd63 && counter_16bit == 4'd15 && odd_even == 1'd1) odd1_wr <= 1'd1;
	else odd1_wr <= 1'd0;
end

always@(posedge clk or posedge reset)
begin
	if(reset) even1_wr <= 1'd0;
	else if(mem_counter <= 8'd63 && counter_16bit == 4'd15 && odd_even == 1'd0) even1_wr <= 1'd1;
	else if(mem_counter <= 8'd63 && counter_16bit == 4'd7 && odd_even == 1'd1) even1_wr <= 1'd1;
	else even1_wr <= 1'd0;
end

always@(posedge clk or posedge reset)
begin
	if(reset) odd2_wr <= 1'd0;
	else if(mem_counter > 8'd63 && mem_counter<=8'd127 && counter_16bit == 4'd7)
	begin
		odd2_wr <= 1'd1;
	end
	else odd2_wr <= 1'd0;
end

always@(posedge clk or posedge reset)
begin
	if(reset) even2_wr <= 1'd0;
	else if(mem_counter > 8'd63 && mem_counter<=8'd127 && counter_16bit == 4'd15)
	begin
		even2_wr <= 1'd1;
	end
	else even2_wr <= 1'd0;
end

always@(posedge clk or posedge reset)
begin
	if(reset) odd3_wr <= 1'd0;
	else if(mem_counter > 8'd127 && mem_counter<=8'd191 && counter_16bit == 4'd7)
	begin
		odd3_wr <= 1'd1;
	end
	else odd3_wr <= 1'd0;
end

always@(posedge clk or posedge reset)
begin
	if(reset) even3_wr <= 1'd0;
	else if(mem_counter > 8'd127 && mem_counter<=8'd191 && counter_16bit == 4'd15)
	begin
		even3_wr <= 1'd1;
	end
	else even3_wr <= 1'd0;
end

always@(posedge clk or posedge reset)
begin
	if(reset) odd4_wr <= 1'd0;
	else if(mem_counter > 8'd191 && mem_counter<=8'd255 && counter_16bit == 4'd7)
	begin
		odd4_wr <= 1'd1;
	end
	else odd4_wr <= 1'd0;
end

always@(posedge clk or posedge reset)
begin
	if(reset) even4_wr <= 1'd0;
	else if(mem_counter > 8'd191 && mem_counter<=8'd255 && counter_16bit == 4'd15)
	begin
		even4_wr <= 1'd1;
	end
	else even4_wr <= 1'd0;
end

endmodule

testfixture1.v
`timescale 1ns/10ps
`define SDFFILE    "./syn/STI_DAC_syn.sdf"    // Modify your sdf file name
`define cycle 10
`define terminate_cycle 100000

module testfixture1;



	`define Pattern "./dat/Pattern.dat"
	`define Stimulus "./dat/Stimulus.dat"
	`define Expected "./dat/Expected_so.dat"
	`define Pat_num 99
	`define Exp_num 1871
	`define Pixel "./dat/Expected_pixel.dat"
	`define odd1 "./dat/Expected_odd_1.dat"
	`define odd2 "./dat/Expected_odd_2.dat"
	`define odd3 "./dat/Expected_odd_3.dat"
	`define odd4 "./dat/Expected_odd_4.dat" 
	`define even1 "./dat/Expected_even_1.dat"
	`define even2 "./dat/Expected_even_2.dat"
	`define even3 "./dat/Expected_even_3.dat"
	`define even4 "./dat/Expected_even_4.dat"



reg [15:0] stimulus_in, pattern_in;

reg Exp_so;

reg pi_end;

reg load, reset;
reg clk = 0;
wire [1:0] pi_length = stimulus_in[13:12];
wire fill_mode = stimulus_in[8];
wire msb_first = stimulus_in[4];
wire low_en = stimulus_in[0];
wire [15:0] pi_data = pattern_in;
wire 		so_data, so_valid;

wire  pixel_finish, pixel_wr, oem_finish, odd1_wr, odd2_wr , odd3_wr , odd4_wr , even1_wr , even2_wr , even3_wr, even4_wr;
wire [7:0] pixel_addr;
wire [7:0] pixel_dataout;
wire [4:0] oem_addr;
wire [7:0] oem_dataout;

integer pp, pixel_err;
reg [7:0] PIXEL_MEM [0 : 233];
integer oo1, oo1_err, oo2, oo2_err, oo3, oo3_err, oo4, oo4_err;
reg [7:0] ODD1_MEM [0 : 31];
reg [7:0] ODD2_MEM [0 : 31];
reg [7:0] ODD3_MEM [0 : 31];
reg [7:0] ODD4_MEM [0 : 31];
integer ee1, ee1_err, ee2, ee2_err, ee3, ee3_err, ee4, ee4_err;
reg [7:0] EVEN1_MEM [0 : 31];
reg [7:0] EVEN2_MEM [0 : 31];
reg [7:0] EVEN3_MEM [0 : 31];
reg [7:0] EVEN4_MEM [0 : 31];
always@(posedge pixel_wr) PIXEL_MEM[pixel_addr] = pixel_dataout;
always@(posedge odd1_wr) ODD1_MEM[oem_addr] = oem_dataout;
always@(posedge odd2_wr) ODD2_MEM[oem_addr] = oem_dataout;
always@(posedge odd3_wr) ODD3_MEM[oem_addr] = oem_dataout;
always@(posedge odd4_wr) ODD4_MEM[oem_addr] = oem_dataout;
always@(posedge even1_wr) EVEN1_MEM[oem_addr] = oem_dataout;
always@(posedge even2_wr) EVEN2_MEM[oem_addr] = oem_dataout;
always@(posedge even3_wr) EVEN3_MEM[oem_addr] = oem_dataout;
always@(posedge even4_wr) EVEN4_MEM[oem_addr] = oem_dataout;

// ---------------------------------------- DUT instance ----------------------------------------------------------------------------------------------------
STI_DAC u_rtl(.clk(clk) ,.reset(reset), .load(load), .pi_data(pi_data), .pi_length(pi_length), 
	      .pi_fill(fill_mode), .pi_msb(msb_first), .pi_low(low_en), .pi_end(pi_end),
	      .so_data(so_data), .so_valid(so_valid),  
	      .oem_finish(oem_finish), .oem_addr(oem_addr), .oem_dataout(oem_dataout), 
	      .odd1_wr(odd1_wr), .odd2_wr(odd2_wr), .odd3_wr(odd3_wr), .odd4_wr(odd4_wr), 
	      .even1_wr(even1_wr), .even2_wr(even2_wr), .even3_wr(even3_wr), .even4_wr(even4_wr));

`ifdef SDF
initial $sdf_annotate(`SDFFILE, u_rtl);
`endif



reg [15:0] 	Pat_memory [0:`Pat_num];
reg 	   	Exp_memory [0:`Exp_num];
reg		Real_memory [0:`Exp_num];
reg [15:0] 	Sti_memory [0:`Pat_num];
reg [7:0] 	Exp_pixel [0:233];
reg [7:0] Exp_odd01 [0:31];
reg [7:0] Exp_odd02 [0:31];
reg [7:0] Exp_odd03 [0:31];
reg [7:0] Exp_odd04 [0:31];
reg [7:0] Exp_even01 [0:31];
reg [7:0] Exp_even02 [0:31];
reg [7:0] Exp_even03 [0:31];
reg [7:0] Exp_even04 [0:31];
initial begin
	$readmemh(`Pattern, Pat_memory);
	$readmemh(`Stimulus, Sti_memory);
	$readmemh(`Expected, Exp_memory);
	$readmemh(`Pixel, Exp_pixel);
	$readmemh(`odd1, Exp_odd01); 
	$readmemh(`odd2, Exp_odd02); 
	$readmemh(`odd3, Exp_odd03); 
	$readmemh(`odd4, Exp_odd04);
	$readmemh(`even1, Exp_even01); 
	$readmemh(`even2, Exp_even02); 
	$readmemh(`even3, Exp_even03); 
	$readmemh(`even4, Exp_even04);
	$display("--------------------------- Simulation Pattern is ready !!---------------------------");
end



always #(`cycle/2) clk = ~clk;

integer k;
integer i;
integer err_cnt;
integer c;
reg so_pass, Real_so, so_exp;
//------------- SPI module test ------------------------------------------------------------------------------------------------------------------------
initial begin
	//$fsdbDumpfile("STI_DAC.fsdb");
	//$fsdbDumpvars;
	$dumpfile("STI_DAC.vcd");
	$dumpvars;
      $display("--------------------------- [ testfuxture1.v ] Simulation START !!---------------------------");
      $timeformat(-9, 1, " ns", 9); //Display time in nanoseconds
      
      err_cnt = 0;   
      reset = 0;
      load = 0;
      # `cycle;
      stimulus_in = 0;
      pattern_in = 0;
      reset = 1; 
      pi_end = 0;
      # `cycle;
      reset = 0; 
      i = 0;
      
        $display("--------------------------- Simulation at parallel data input stage !!---------------------------");
	for (k = 0; k <= `Pat_num; k = k+1)
	begin      
		
			@(negedge clk)
			//change inputs at strobe point
          		#(`cycle/4) load = 1;
				stimulus_in = Sti_memory[k];                
      				pattern_in = Pat_memory[k];
			#(`cycle) load = 0;
          		//Wait for PSI to process inputs
			if (k==`Pat_num) pi_end = 1;
          		wait(so_valid) 
			record_outputs; //call a task to verify outputs
	
	end
	
	// check_outputs	
	$display("--------------------------- Simulation at serial data output and result verify !! ---------------------------");
	for (c = 0; c <= `Exp_num; c = c+1) 
	begin
		
		if (Real_memory[c] == Exp_memory[c]) begin  so_pass = Real_memory[c]; so_exp =  Exp_memory[c]; end
		else begin err_cnt = err_cnt + 1;  
			$display("---------- ERROR at pattern No. %d,  REAL OUTPUT : so_data = %b,  EXPECTED OUTPUT so_data = %b\n",
      			c, Real_memory[c], Exp_memory[c]); end
	end 
	
     #`cycle 
     $display("--------------------------- so_data simulation FINISH !!---------------------------");
     if (err_cnt) begin 
     	$display("============================================================================");
     	$display("\n (T_T)  The simulation result of so_data is FAIL!!! there were %d errors in all.\n", err_cnt);
	$display("============================================================================");
	end
     else begin 
     	$display("============================================================================");
	$display("\n \\(^o^)/  The simulation result of so_data is PASS!!!\n");
	$display("============================================================================");
	end
     wait ( oem_finish );
     #(`cycle*0.25) ;
     $display("--------------------------- OM-memory and EM-memory simulation FINISH !!---------------------------");
     if ( oo1_err || oo2_err || oo3_err || oo4_err || ee1_err || ee2_err || ee3_err || ee4_err) begin 
     	$display("============================================================================");
     	$display("\n (T_T)  The simulation result of OM-memory and EM-memory is FAIL!!! Please debug your RTL code !!.\n");
	$display("============================================================================");
	end
     else begin 
     	$display("============================================================================");
	$display("\n \\(^o^)/  The simulation result of OM-memory and EM-memory is PASS!!!\n");
	$display("============================================================================");
	end
     //#`cycle    
     $finish;
end


initial begin 
	#`terminate_cycle;
	$display("================================================================================================================");
	$display("--------------------------- (/`n`)/ ~#  There was something wrong with your code !! ---------------------------"); 
	$display("--------------------------- The simulation can't finished!!, Please check it !!! ---------------------------"); 
	$display("================================================================================================================");
	$finish;
end

//--------------------------- check SPI outputs -----------------------------------------------------------------
  task record_outputs;	
  	while(so_valid)  begin
  		@(negedge clk); 
		if (so_valid) begin
		Real_memory[i] = so_data;
		Real_so = Real_memory[i];
		i = i+1;
  		end
	end 
  endtask




//=========================================================================================================================================
//=========================================================================================================================================
//=========================================================================================================================================
//----------------------- Check Pixel data -----------------------------------------------------------------------------------------------------

/*
initial begin
	pixel_err  = 0;
	wait(pixel_finish)
	for (pp=0; pp<=233; pp=pp+1) begin
		if (Exp_pixel[pp] == PIXEL_MEM[pp]);
		else begin
			pixel_err = pixel_err + 1;
			$display("---------- ERROR AT %t,  ERROR DATA : the real data at pixel address %d = %h,  EXPECTED DATA  = %h\n",
			$realtime, pp, PIXEL_MEM[pp], Exp_pixel[pp]);
		end
	end
end
*/
//----------------------- Check EVEN memory -----------------------------------------------------------------------------------------------------
initial begin
	ee4_err = 0;
	wait(reset); wait(!reset); wait(load); wait(!load);
	wait(oem_finish);
	for (ee4=0; ee4<=31; ee4=ee4+1) begin
		if (Exp_even04[ee4] == EVEN4_MEM[ee4]);
		else begin
			ee4_err = ee4_err + 1;
			$display("---------- ERROR AT %t,  ERROR DATA : the real data  at EVEN4_MEM address %d = %h, but the EXPECTED DATA  is %h\n",
			$realtime, ee4, EVEN4_MEM[ee4], Exp_even04[ee4]);
		end
	end
end
initial begin
	ee3_err = 0;
	wait(reset); wait(!reset); wait(load); wait(!load);
	wait(oem_finish);
	for (ee3=0; ee3<=31; ee3=ee3+1) begin
		if (Exp_even03[ee3] == EVEN3_MEM[ee3]);
		else begin
			ee3_err = ee3_err + 1;
			$display("---------- ERROR AT %t,  ERROR DATA : the real data at EVEN3_MEM address %d = %h, but the EXPECTED DATA  is %h\n",
			$realtime, ee3, EVEN3_MEM[ee3], Exp_even03[ee3]);
		end
	end
end
initial begin
	ee2_err = 0;
	wait(reset); wait(!reset); wait(load); wait(!load);
	wait(oem_finish);
	for (ee2=0; ee2<=31; ee2=ee2+1) begin
		if (Exp_even02[ee2] == EVEN2_MEM[ee2]);
		else begin
			ee2_err = ee2_err + 1;
			$display("---------- ERROR AT %t,  ERROR DATA : the real data at EVEN2_MEM address %d = %h, but the EXPECTED DATA  is %h\n",
			$realtime, ee2, EVEN2_MEM[ee2], Exp_even02[ee2]);
		end
	end
end
initial begin
	ee1_err = 0;
	wait(reset); wait(!reset); wait(load); wait(!load);
	wait(oem_finish);
	for (ee1=0; ee1<=31; ee1=ee1+1) begin
		if (Exp_even01[ee1] == EVEN1_MEM[ee1]);
		else begin
			ee1_err = ee1_err + 1;
			$display("---------- ERROR AT %t,  ERROR DATA : the real data at EVEN1_MEM address %d = %h, but the EXPECTED DATA  is %h\n",
			$realtime, ee1, EVEN1_MEM[ee1], Exp_even01[ee1]);
		end
	end
end

//----------------------- Check ODD memory -----------------------------------------------------------------------------------------------------
initial begin
	oo4_err = 0;
	wait(reset); wait(!reset); wait(load); wait(!load);
	wait(oem_finish);
	for (oo4=0; oo4<=31; oo4=oo4+1) begin
		if (Exp_odd04[oo4] == ODD4_MEM[oo4]);
		else begin
			oo4_err = oo4_err + 1;
			$display("---------- ERROR AT %t,  ERROR DATA : the real data at ODD4_MEM address %d = %h, but the EXPECTED DATA  is %h\n",
			$realtime, oo4, ODD4_MEM[oo4], Exp_odd04[oo4]);
		end
	end
end
initial begin
	oo3_err = 0;
	wait(reset); wait(!reset); wait(load); wait(!load);
	wait(oem_finish);
	for (oo3=0; oo3<=31; oo3=oo3+1) begin 
		if (Exp_odd03[oo3] == ODD3_MEM[oo3]);
		else begin
			oo3_err = oo3_err + 1;
			$display("---------- ERROR AT %t,  ERROR DATA : the real data at ODD3_MEM address %d = %h, but the EXPECTED DATA  = %h\n",
			$realtime, oo3, ODD3_MEM[oo3], Exp_odd03[oo3]);
		end
	end
end
initial begin
	oo2_err = 0;
	wait(reset); wait(!reset); wait(load); wait(!load);
	wait(oem_finish);
	for (oo2=0; oo2<=31; oo2=oo2+1) begin
		if (Exp_odd02[oo2] == ODD2_MEM[oo2]);
		else begin
			oo2_err = oo2_err + 1;
			$display("---------- ERROR AT %t,  ERROR DATA : the real data at ODD2_MEM address %d = %h, but the EXPECTED DATA  is %h\n",
			$realtime, oo2, ODD2_MEM[oo2], Exp_odd02[oo2]);
		end
	end
end
initial begin
	oo1_err = 0;
	wait(reset); wait(!reset); wait(load); wait(!load);
	wait(oem_finish);
	for (oo1=0; oo1<=31; oo1=oo1+1) begin
		if (Exp_odd01[oo1] == ODD1_MEM[oo1]);
		else begin
			oo1_err = oo1_err + 1;
			$display("---------- ERROR AT %t,  ERROR DATA : the real data at ODD1_MEM address %d = %h, but the EXPECTED DATA  is %h\n",
			$realtime, oo1, ODD1_MEM[oo1], Exp_odd01[oo1]);
		end
	end
end








endmodule

STI_DAC.vcd
$date
	Mon Aug 31 18:44:53 2020
$end
$version
	Icarus Verilog
$end
$timescale
	10ps
$end
$scope module testfixture1 $end
$var wire 16 ! pi_data [15:0] $end
$var wire 8 " pixel_addr [7:0] $end
$var wire 8 # pixel_dataout [7:0] $end
$var wire 1 $ pixel_wr $end
$var wire 1 % so_valid $end
$var wire 1 & so_data $end
$var wire 2 ' pi_length [1:0] $end
$var wire 1 ( oem_finish $end
$var wire 8 ) oem_dataout [7:0] $end
$var wire 5 * oem_addr [4:0] $end
$var wire 1 + odd4_wr $end
$var wire 1 , odd3_wr $end
$var wire 1 - odd2_wr $end
$var wire 1 . odd1_wr $end
$var wire 1 / msb_first $end
$var wire 1 0 low_en $end
$var wire 1 1 fill_mode $end
$var wire 1 2 even4_wr $end
$var wire 1 3 even3_wr $end
$var wire 1 4 even2_wr $end
$var wire 1 5 even1_wr $end
$var reg 1 6 Real_so $end
$var reg 1 7 clk $end
$var reg 1 8 load $end
$var reg 16 9 pattern_in [15:0] $end
$var reg 1 : pi_end $end
$var reg 1 ; reset $end
$var reg 1 < so_exp $end
$var reg 1 = so_pass $end
$var reg 16 > stimulus_in [15:0] $end
$var integer 32 ? c [31:0] $end
$var integer 32 @ ee1 [31:0] $end
$var integer 32 A ee1_err [31:0] $end
$var integer 32 B ee2 [31:0] $end
$var integer 32 C ee2_err [31:0] $end
$var integer 32 D ee3 [31:0] $end
$var integer 32 E ee3_err [31:0] $end
$var integer 32 F ee4 [31:0] $end
$var integer 32 G ee4_err [31:0] $end
$var integer 32 H err_cnt [31:0] $end
$var integer 32 I i [31:0] $end
$var integer 32 J k [31:0] $end
$var integer 32 K oo1 [31:0] $end
$var integer 32 L oo1_err [31:0] $end
$var integer 32 M oo2 [31:0] $end
$var integer 32 N oo2_err [31:0] $end
$var integer 32 O oo3 [31:0] $end
$var integer 32 P oo3_err [31:0] $end
$var integer 32 Q oo4 [31:0] $end
$var integer 32 R oo4_err [31:0] $end
$scope module u_rtl $end
$var wire 1 7 clk $end
$var wire 1 8 load $end
$var wire 8 S oem_dataout [7:0] $end
$var wire 16 T pi_data [15:0] $end
$var wire 1 : pi_end $end
$var wire 1 1 pi_fill $end
$var wire 2 U pi_length [1:0] $end
$var wire 1 0 pi_low $end
$var wire 1 / pi_msb $end
$var wire 1 ; reset $end
$var reg 8 V DAC_buffer [7:0] $end
$var reg 4 W counter_16bit [3:0] $end
$var reg 3 X current_state [2:0] $end
$var reg 32 Y data_buffer [31:0] $end
$var reg 5 Z data_buffer_index [4:0] $end
$var reg 5 [ delay_buffer [4:0] $end
$var reg 1 5 even1_wr $end
$var reg 1 4 even2_wr $end
$var reg 1 3 even3_wr $end
$var reg 1 2 even4_wr $end
$var reg 8 \ mem_counter [7:0] $end
$var reg 3 ] next_state [2:0] $end
$var reg 1 . odd1_wr $end
$var reg 1 - odd2_wr $end
$var reg 1 , odd3_wr $end
$var reg 1 + odd4_wr $end
$var reg 1 ^ odd_even $end
$var reg 5 _ oem_addr [4:0] $end
$var reg 1 ( oem_finish $end
$var reg 5 ` pi_length_bit [4:0] $end
$var reg 5 a serial_counter [4:0] $end
$var reg 1 & so_data $end
$var reg 1 % so_valid $end
$upscope $end
$scope task record_outputs $end
$upscope $end
$upscope $end
$enddefinitions $end
#0
$dumpvars
bx a
bx `
bx _
x^
b0 ]
bx \
bx [
bx Z
bx Y
bx X
bx W
bx V
bx U
bx T
bx S
b0 R
bx Q
b0 P
bx O
b0 N
bx M
b0 L
bx K
bx J
bx I
b0 H
b0 G
bx F
b0 E
bx D
b0 C
bx B
b0 A
bx @
bx ?
bx >
x=
x<
0;
x:
bx 9
08
07
x6
x5
x4
x3
x2
x1
x0
x/
x.
x-
x,
x+
bx *
bx )
x(
bx '
x&
x%
z$
bz #
bz "
bx !
$end
#500
b0 X
0%
0.
05
0-
04
0,
03
0+
02
17
#1000
0(
b0 *
b0 _
b0 [
b0 \
b0 W
b0 )
b0 S
b0 V
0^
0&
b11111 a
b111 `
b0 Z
b0 Y
b0 '
b0 U
01
0/
00
07
0:
1;
b0 !
b0 T
b0 9
b0 >
#1500
17
#2000
07
b0 J
b0 I
0;
#2200
b1111 `
b100000000100000000000000000 Y
b1 '
b1 U
10
b1 ]
b10000000010 !
b10000000010 T
b10000000010 9
b1000000000001 >
18
#2500
b10 ]
b10000 Z
b1111 a
b1 X
17
#3000
07
#3200
08
#3500
b10 X
1%
b10001 Z
17
#4000
b1 I
06
07
#4500
b1 W
1&
b10010 Z
b1110 a
17
#5000
b10 I
16
07
#5500
b1101 a
b10011 Z
0&
b1 )
b1 S
b1 V
b10 W
17
#6000
b11 I
06
07
#6500
b11 W
b10 )
b10 S
b10 V
b10100 Z
b1100 a
17
#7000
b100 I
07
#7500
b1011 a
b10101 Z
b100 )
b100 S
b100 V
b100 W
17
#8000
b101 I
07
#8500
b101 W
b1000 )
b1000 S
b1000 V
b10110 Z
b1010 a
17
#9000
b110 I
07
#9500
b1001 a
b10111 Z
b10000 )
b10000 S
b10000 V
b110 W
17
#10000
b111 I
07
#10500
b111 W
b100000 )
b100000 S
b100000 V
b11000 Z
b1000 a
17
#11000
b1000 I
07
#11500
b111 a
b11001 Z
b1000000 )
b1000000 S
b1000000 V
b1000 W
b1 \
1.
17
#12000
b1001 I
07
#12500
0.
b1001 W
b10000000 )
b10000000 S
b10000000 V
b11010 Z
b110 a
17
#13000
b1010 I
07
#13500
b101 a
b11011 Z
1&
b0 )
b0 S
b0 V
b1010 W
17
#14000
b1011 I
16
07
#14500
b1011 W
b1 )
b1 S
b1 V
0&
b11100 Z
b100 a
17
#15000
b1100 I
06
07
#15500
b11 a
b11101 Z
b10 )
b10 S
b10 V
b1100 W
17
#16000
b1101 I
07
#16500
b1101 W
b100 )
b100 S
b100 V
b11110 Z
b10 a
17
#17000
b1110 I
07
#17500
b1 a
b11111 Z
b1000 )
b1000 S
b1000 V
b1110 W
17
#18000
b1111 I
07
#18500
b0 ]
b1111 W
b10000 )
b10000 S
b10000 V
b0 Z
b0 a
17
#19000
b10000 I
07
#19500
b0 X
b11111 a
0%
b100000 )
b100000 S
b100000 V
b0 W
b10 \
b1 [
15
17
#20000
b1 J
07
#20500
05
b1 *
b1 _
17
#21000
07
#21200
b111 `
b101110000000000000000000000000 Y
b0 '
b0 U
00
b1 ]
b101110 !
b101110 T
b101110 9
b0 >
18
#21500
b10 ]
b1 X
b111 a
b11000 Z
17
#22000
07
#22200
08
#22500
b11001 Z
1%
b10 X
17
#23000
b10001 I
07
#23500
b110 a
b11010 Z
1&
b1000000 )
b1000000 S
b1000000 V
b1 W
17
#24000
b10010 I
16
07
#24500
b10 W
b10000001 )
b10000001 S
b10000001 V
b11011 Z
b101 a
17
#25000
b10011 I
07
#25500
b100 a
b11100 Z
b11 )
b11 S
b11 V
b11 W
17
#26000
b10100 I
07
#26500
b100 W
b111 )
b111 S
b111 V
0&
b11101 Z
b11 a
17
#27000
b10101 I
06
07
#27500
b10 a
b11110 Z
1&
b1110 )
b1110 S
b1110 V
b101 W
17
#28000
b10110 I
16
07
#28500
b110 W
b11101 )
b11101 S
b11101 V
0&
b11111 Z
b1 a
17
#29000
b10111 I
06
07
#29500
b0 ]
b0 a
b0 Z
b111010 )
b111010 S
b111010 V
b111 W
17
#30000
b11000 I
07
#30500
1.
b11 \
b1000 W
b1110100 )
b1110100 S
b1110100 V
0%
b11111 a
b0 X
17
#31000
b10 J
07
#31500
0.
17
#32000
07
#32200
b1111 `
b11000000000000000000000 Y
b1 '
b1 U
b1 ]
b1100000 !
b1100000 T
b1100000 9
b1000000000000 >
18
#32500
b10 ]
b10000 Z
b1111 a
b1 X
17
#33000
07
#33200
08
#33500
b10 X
1%
b10001 Z
17
#34000
b11001 I
07
#34500
b1001 W
b11101000 )
b11101000 S
b11101000 V
b10010 Z
b1110 a
17
#35000
b11010 I
07
#35500
b1101 a
b10011 Z
b11010000 )
b11010000 S
b11010000 V
b1010 W
17
#36000
b11011 I
07
#36500
b1011 W
b10100000 )
b10100000 S
b10100000 V
b10100 Z
b1100 a
17
#37000
b11100 I
07
#37500
b1011 a
b10101 Z
b1000000 )
b1000000 S
b1000000 V
b1100 W
17
#38000
b11101 I
07
#38500
b1101 W
b10000000 )
b10000000 S
b10000000 V
1&
b10110 Z
b1010 a
17
#39000
b11110 I
16
07
#39500
b1001 a
b10111 Z
b1 )
b1 S
b1 V
b1110 W
17
#40000
b11111 I
07
#40500
b1111 W
b11 )
b11 S
b11 V
0&
b11000 Z
b1000 a
17
#41000
b100000 I
06
07
#41500
b111 a
b11001 Z
b110 )
b110 S
b110 V
b0 W
b100 \
b10 [
15
17
#42000
b100001 I
07
#42500
05
b10 *
b10 _
b1 W
b1100 )
b1100 S
b1100 V
b11010 Z
b110 a
17
#43000
b100010 I
07
#43500
b101 a
b11011 Z
b11000 )
b11000 S
b11000 V
b10 W
17
#44000
b100011 I
07
#44500
b11 W
b110000 )
b110000 S
b110000 V
b11100 Z
b100 a
17
#45000
b100100 I
07
#45500
b11 a
b11101 Z
b1100000 )
b1100000 S
b1100000 V
b100 W
17
#46000
b100101 I
07
#46500
b101 W
b11000000 )
b11000000 S
b11000000 V
b11110 Z
b10 a
17
#47000
b100110 I
07
#47500
b1 a
b11111 Z
b10000000 )
b10000000 S
b10000000 V
b110 W
17
#48000
b100111 I
07
#48500
b0 ]
b111 W
b0 )
b0 S
b0 V
b0 Z
b0 a
17
